pelican_manager/__init__.py
pelican_manager/__main__.py
pelican_manager/__version__.py
pelican_manager/article.py
pelican_manager/config.py
pelican_manager/forms.py
pelican_manager/utils.py
pelican_manager/views.py
pelican_manager/config/defaultconf.py
pelican_manager/static/bootstrap-table/.gitignore
pelican_manager/static/bootstrap-table/.travis.yml
pelican_manager/static/bootstrap-table/CHANGELOG.md
pelican_manager/static/bootstrap-table/CONTRIBUTING.md
pelican_manager/static/bootstrap-table/DONATORS.md
pelican_manager/static/bootstrap-table/Gruntfile.js
pelican_manager/static/bootstrap-table/LICENSE
pelican_manager/static/bootstrap-table/README.md
pelican_manager/static/bootstrap-table/_config.yml
pelican_manager/static/bootstrap-table/bootstrap-table.jquery.json
pelican_manager/static/bootstrap-table/bower.json
pelican_manager/static/bootstrap-table/composer.json
pelican_manager/static/bootstrap-table/package.json
pelican_manager/static/bootstrap-table/.github/ISSUE_TEMPLATE.md
pelican_manager/static/bootstrap-table/dist/bootstrap-table-locale-all.js
pelican_manager/static/bootstrap-table/dist/bootstrap-table-locale-all.min.js
pelican_manager/static/bootstrap-table/dist/bootstrap-table.css
pelican_manager/static/bootstrap-table/dist/bootstrap-table.js
pelican_manager/static/bootstrap-table/dist/bootstrap-table.min.css
pelican_manager/static/bootstrap-table/dist/bootstrap-table.min.js
pelican_manager/static/bootstrap-table/dist/extensions/accent-neutralise/bootstrap-table-accent-neutralise.js
pelican_manager/static/bootstrap-table/dist/extensions/accent-neutralise/bootstrap-table-accent-neutralise.min.js
pelican_manager/static/bootstrap-table/dist/extensions/angular/bootstrap-table-angular.js
pelican_manager/static/bootstrap-table/dist/extensions/angular/bootstrap-table-angular.min.js
pelican_manager/static/bootstrap-table/dist/extensions/auto-refresh/bootstrap-table-auto-refresh.css
pelican_manager-0.2.1.dist-info/DESCRIPTION.rst
pelican_manager-0.2.1.dist-info/METADATA
pelican_manager-0.2.1.dist-info/RECORD
pelican_manager-0.2.1.dist-info/WHEEL
pelican_manager-0.2.1.dist-info/entry_points.txt
pelican_manager-0.2.1.dist-info/metadata.json
pelican_manager-0.2.1.dist-info/top_level.txt
